zaturn/mcp/__init__.py
zaturn/studio/__init__.py
zaturn/studio/agent_wrapper.py
zaturn/studio/app.py
zaturn/studio/storage.py
zaturn/studio/static/fira_code.ttf
zaturn/studio/static/inter_ital_var.ttf
zaturn/studio/static/inter_var.ttf
zaturn/studio/static/logo.png
zaturn/studio/static/logo.svg
zaturn/studio/static/js/htmx-multi-swap.js
zaturn/studio/static/js/htmx.min.js
zaturn/studio/templates/_shell.html
zaturn/studio/templates/ai_message.html
zaturn/studio/templates/c_settings_updated.html
zaturn/studio/templates/c_source_card.html
zaturn/studio/templates/chat.html
zaturn/studio/templates/chat_metadata.html
zaturn/studio/templates/function_call.html
zaturn/studio/templates/loader.html
zaturn/studio/templates/manage_sources.html
zaturn/studio/templates/nav.html
zaturn/studio/templates/new_conversation.html
zaturn/studio/templates/settings.html
zaturn/studio/templates/setup_prompt.html
zaturn/studio/templates/user_message.html
zaturn/studio/templates/css/style.css
zaturn/studio/templates/icons/arrow-left.svg
zaturn/studio/templates/icons/arrow-right.svg
zaturn/studio/templates/icons/chat-bubble.svg
zaturn/studio/templates/icons/check-circle-solid.svg
zaturn/studio/templates/icons/database.svg
zaturn/studio/templates/icons/fire-flame.svg
zaturn/studio/templates/icons/floppy-disk.svg
zaturn/studio/templates/icons/link.svg
zaturn/studio/templates/icons/play.svg
zaturn/studio/templates/icons/settings.svg
zaturn/studio/templates/icons/timer.svg
zaturn/studio/templates/icons/trash.svg
zaturn/studio/templates/icons/upload.svg
zaturn/studio/templates/icons/user.svg
zaturn/studio/templates/icons/warning-triangle.svg
zaturn/studio/templates/icons/wrench.svg
zaturn/tools/__init__.py
zaturn/tools/config.py
zaturn/tools/core.py
zaturn/tools/query_utils.py
zaturn/tools/visualizations.py
zaturn/tools/example_data/all_pokemon_data.csv
zaturn-0.4.0.dist-info/licenses/LICENSE
zaturn-0.4.0.dist-info/METADATA
zaturn-0.4.0.dist-info/WHEEL
zaturn-0.4.0.dist-info/entry_points.txt
zaturn-0.4.0.dist-info/top_level.txt
zaturn-0.4.0.dist-info/RECORD
