Metadata-Version: 2.4
Name: zaturn
Version: 0.4.0
Summary: AI Data Analysis MCP & Studio
Author-email: Karthik Devan <krtdvn@gmail.com>
Maintainer-email: Karthik Devan <krtdvn@gmail.com>
Project-URL: Homepage, https://github.com/kdqed/zaturn
Project-URL: Issues, https://github.com/kdqed/zaturn/issues
Requires-Python: >=3.11
License-File: LICENSE
Requires-Dist: clickhouse-connect>=0.8.17
Requires-Dist: cryptography>=44.0.2
Requires-Dist: db-dtypes>=1.4.3
Requires-Dist: duckdb>=1.2.1
Requires-Dist: fastmcp>=0.4.1
Requires-Dist: flask[async]>=3.1.1
Requires-Dist: function-schema>=0.4.5
Requires-Dist: google-auth>=2.40.3
Requires-Dist: google-cloud-bigquery>=3.38.0
Requires-Dist: kaleido==0.2.1
Requires-Dist: mistune>=3.1.3
Requires-Dist: openai>=1.82.1
Requires-Dist: pandas>=2.2.3
Requires-Dist: pillow>=11.2.1
Requires-Dist: platformdirs>=4.3.7
Requires-Dist: plotly[express]>=6.0.1
Requires-Dist: psycopg2-binary>=2.9.10
Requires-Dist: pyarrow>=19.0.1
Requires-Dist: pydantic-ai>=0.8.0
Requires-Dist: pydantic-core>=2.33.2
Requires-Dist: pymssql>=2.3.7
Requires-Dist: pymysql>=1.1.1
Requires-Dist: python-lsp-server>=1.12.2
Requires-Dist: python-slugify>=8.0.4
Requires-Dist: seaborn>=0.13.2
Requires-Dist: setuptools>=78.1.0
Requires-Dist: sqlalchemy>=2.0.40
Requires-Dist: tabulate>=0.9.0
Requires-Dist: tomli-w>=1.2.0
Requires-Dist: werkzeug>=3.1.3
Dynamic: license-file
